{
    "topic_id": 118284544452152,
    "group": {
        "group_id": 1824528822,
        "name": "生财有术"
    },
    "type": "talk",
    "talk": {
        "owner": {
            "user_id": 552158581144,
            "name": "亦仁",
            "alias": "亦仁",
            "avatar_url": "https://images.zsxq.com/Fn3NQqCN8nuGF86yZPXSbEsl0mb3?e=1590940799&token=kIxbL07-8jAj8w1n4s9zv64FuZZNEATmlU_Vm6zD:pfbNc8W3hS0oYG_hyXXh_rHMHuc=",
            "description": "一直在路上的创业者，「生财有术」星主，公众号「亦无所知」，个人微信号：yirenpro"
        },
        "text": "<e type=\"web\" href=\"https%3A%2F%2Fmp.weixin.qq.com%2Fs%2FlBZjppE5cwvNs9EfVHcTgg\" title=\"%E7%8B%AC%E5%AE%B6+%7C+%E9%98%BF%E9%87%8C%E5%BC%A0%E5%8B%87%E6%B9%96%E7%95%94%E5%88%86%E4%BA%AB%EF%BC%9A%E9%A2%86%E5%AF%BC%E8%80%85%E5%A6%82%E4%BD%95%E2%80%9C%E8%90%BD%E5%AD%90%E6%97%A0%E6%82%94%E2%80%9D\" cache=\"\" />\n\n值得反复读，不理解的点先种下一颗种子，慢慢的有一天可能就会理解。\n\n“1. 第一天就想做平台的人，基本上都没做成。\n选赛道通常两种方式：一种是垂直整合，另一种是水平延展。\n\n2. 所谓“落子无悔”，有些决定别人不可能替你做，只有一号位责无旁贷。 \n\n3. 企图通过共创会解决企业战略发展问题的，是领导者无能的表现。\n\n4. 以解决信息不对称性而创造的业务，未来终将消失。\n\n5. 市场是动态的，要在动态中防止焦虑，保持战略定力。地球是圆的，往东坚持到最后，只要你还活着，就是往西。\n\n6. 最大的确定性就是不确定性，真正的业务一号位，一定是在高度的不确定性当中去寻找确定性。\n\n7. 要把能努力的都努力好之后，最终等待命运垂青。\n\n8. 领导者不是万能的，领导者注定孤独。面向未来，不仅要看未来的机会，同时也看未来的问题。\n\n9. 当一个机会变成广泛共识的时候，是最需要小心的时候。绝望当中都是机会，冲动当中都是陷阱。\n\n10. 绝大多数的协同问题都不是态度问题，而是生产关系没设计到位。要在一个扭曲的生产关系下，希望大家一起合作，本身就违反人性。\n\n11. 中台是沉淀出来的，不是从底下长起来的，底下长不起来中台。\n\n12. 经营核心是突破，管理核心是效率。经营和管理永远是“科学+艺术”。留白是一种艺术，必须给客观世界留一些空间。\n\n13. 有时候要付出一些代价，针对不确定性的不同意见，就会变成确定性的一致意见。\n\n14. 做取舍的过程，就是建立信用和消费信用的过程。\n\n15. 老板是封的，是任命的，老大是发自团队内心的。\n\n16. 领导者就是要敢做别人不敢做的决定；承担不能让团队承担，团队也承担不起的责任；搞定团队搞定不了的资源。”"
    },
    "latest_likes": [
        {
            "create_time": "2020-03-15T01:13:25.514+0800",
            "owner": {
                "user_id": 28288442512521,
                "name": "根根是大圣",
                "alias": "根根",
                "avatar_url": "https://images.zsxq.com/FnegxigtN_CLjEJ4WpuWE1-BhZNu?e=1590940799&token=kIxbL07-8jAj8w1n4s9zv64FuZZNEATmlU_Vm6zD:XrJaSOSyXB1TFNoNlx495Z_7DdU=",
                "number": 6872
            }
        },
        {
            "create_time": "2020-02-24T18:51:28.283+0800",
            "owner": {
                "user_id": 455588425888,
                "name": "游乐鱼",
                "avatar_url": "https://images.zsxq.com/FqIieQIcpixYMTzsMBfO3Nx03T5t?e=1590940799&token=kIxbL07-8jAj8w1n4s9zv64FuZZNEATmlU_Vm6zD:mdc7PFps5QFeNqZi4ThJnNbEirU=",
                "number": 6264
            }
        },
        {
            "create_time": "2020-02-15T15:58:34.637+0800",
            "owner": {
                "user_id": 48812588225218,
                "name": "傅超人",
                "avatar_url": "https://images.zsxq.com/Fsj8n5BCabzlDRXyFu1MmjMJ4nlk?e=1590940799&token=kIxbL07-8jAj8w1n4s9zv64FuZZNEATmlU_Vm6zD:XHuYQZhhXQsSDuvRx25zvl1PklY=",
                "number": 2824
            }
        },
        {
            "create_time": "2020-02-08T02:51:50.635+0800",
            "owner": {
                "user_id": 518122858144,
                "name": "hehe",
                "avatar_url": "https://images.zsxq.com/FnX5BdbMSRSXKcoqOrA_YvGFecdr?e=1590940799&token=kIxbL07-8jAj8w1n4s9zv64FuZZNEATmlU_Vm6zD:HOALW3w90PlKBUY1ekYYc-EtBMw=",
                "number": 6263
            }
        },
        {
            "create_time": "2020-01-21T14:54:15.252+0800",
            "owner": {
                "user_id": 458825221158,
                "name": "方舟",
                "avatar_url": "https://images.zsxq.com/FmI0Vd3GXwLfZ-1_aCtXAX82ny0c?e=1590940799&token=kIxbL07-8jAj8w1n4s9zv64FuZZNEATmlU_Vm6zD:yJnYrBbFCtHTIHbWNRDzqhXUaYs=",
                "number": 6622
            }
        },
        {
            "create_time": "2020-01-08T10:55:27.077+0800",
            "owner": {
                "user_id": 1154245422,
                "name": "彼令",
                "avatar_url": "https://images.zsxq.com/FmPezX4Z6x0-vbVPJ_WkhT8zId8F?e=1590940799&token=kIxbL07-8jAj8w1n4s9zv64FuZZNEATmlU_Vm6zD:WinCeFnVBZO3rxR_o6Dympv7Z2k=",
                "number": 6636
            }
        },
        {
            "create_time": "2019-12-30T09:05:24.181+0800",
            "owner": {
                "user_id": 4225154218,
                "name": "冷采",
                "avatar_url": "https://images.zsxq.com/Fi08nVEN5kYkYdM76iX1SNH-3ss2?e=1590940799&token=kIxbL07-8jAj8w1n4s9zv64FuZZNEATmlU_Vm6zD:aiAIIpeF6YB3O8KqDjXbGyvC6D8=",
                "number": 4764
            }
        },
        {
            "create_time": "2019-12-30T07:45:42.451+0800",
            "owner": {
                "user_id": 8488548442,
                "name": "PengPeng",
                "avatar_url": "https://images.zsxq.com/FrOJVRVBhWxnu68iLChtezBeJ5yL?e=1590940799&token=kIxbL07-8jAj8w1n4s9zv64FuZZNEATmlU_Vm6zD:IhetccuC0bjsIn0B5Pqcn1XcRAc=",
                "number": 2574
            }
        },
        {
            "create_time": "2019-12-29T09:43:37.495+0800",
            "owner": {
                "user_id": 225818541441,
                "name": "A℡zoe",
                "avatar_url": "https://images.zsxq.com/FgQcO7zlukgfSnX3u8Ggd_PIDq3x?e=1590940799&token=kIxbL07-8jAj8w1n4s9zv64FuZZNEATmlU_Vm6zD:WujGDi6kF1x4yqmTwNK4uQ7QjC0=",
                "number": 4488
            }
        },
        {
            "create_time": "2019-12-28T11:08:44.805+0800",
            "owner": {
                "user_id": 141444255112,
                "name": "王煜",
                "avatar_url": "https://images.zsxq.com/Fln6LKIQviciO5EoqzblXoKOMZU9?e=1590940799&token=kIxbL07-8jAj8w1n4s9zv64FuZZNEATmlU_Vm6zD:mtHOl5ymAK9xuu1OT3NoyIzFa2Q=",
                "number": 1181
            }
        }
    ],
    "rewards": [
        {
            "create_time": "2019-12-30T22:30:20.641+0800",
            "owner": {
                "user_id": 454218544518,
                "name": "Bluekou",
                "alias": "Bluekou-温虾米",
                "avatar_url": "https://images.zsxq.com/FoDXBpsrCgE7yn77Yd40E8lqqul1?e=1590940799&token=kIxbL07-8jAj8w1n4s9zv64FuZZNEATmlU_Vm6zD:z4sURrvi8iaGNT3lMItHCvvQiFo="
            },
            "amount": 939
        },
        {
            "create_time": "2019-12-27T20:01:22.147+0800",
            "owner": {
                "user_id": 51541512414524,
                "name": "windle",
                "avatar_url": "https://images.zsxq.com/FjLbVwgDYQZ8p57h7srz71pTgW0K?e=1590940799&token=kIxbL07-8jAj8w1n4s9zv64FuZZNEATmlU_Vm6zD:X32nxjwhkBZkVunoPy2qtLjMUHU="
            },
            "amount": 94
        },
        {
            "create_time": "2019-12-27T10:33:01.019+0800",
            "owner": {
                "user_id": 551515481184,
                "name": "桃翁",
                "avatar_url": "https://images.zsxq.com/FnjgfAL-Ep5ouBxB6XnTJF7kwMJL?e=1590940799&token=kIxbL07-8jAj8w1n4s9zv64FuZZNEATmlU_Vm6zD:40rf0ueK1O9jqD-g3vgCbFx_oTk="
            },
            "amount": 252
        },
        {
            "create_time": "2019-12-27T08:55:14.201+0800",
            "owner": {
                "user_id": 88224111882812,
                "name": "夕歌",
                "alias": "夕歌",
                "avatar_url": "https://images.zsxq.com/FmbXV_gjvIdXdHprQ0zXAjCZ8lSl?e=1590940799&token=kIxbL07-8jAj8w1n4s9zv64FuZZNEATmlU_Vm6zD:BcVOwG69B3l3T1eSP2aqfqmlP-4="
            },
            "amount": 188
        },
        {
            "create_time": "2019-12-27T07:41:01.658+0800",
            "owner": {
                "user_id": 5581144214,
                "name": "1/0 二事",
                "avatar_url": "https://images.zsxq.com/Fpz6Vv35TuDuqoyqYcuE0Wed4JXh?e=1590940799&token=kIxbL07-8jAj8w1n4s9zv64FuZZNEATmlU_Vm6zD:oDr8c2PNXSB-TYhug9EVkMu6jUU="
            },
            "amount": 365
        },
        {
            "create_time": "2019-12-27T00:02:27.803+0800",
            "owner": {
                "user_id": 88214125888252,
                "name": "荔枝小一萌",
                "avatar_url": "https://images.zsxq.com/FhlCVRdrm704WvF0MSDb7gVjILZ-?e=1590940799&token=kIxbL07-8jAj8w1n4s9zv64FuZZNEATmlU_Vm6zD:cvFyOyCG5vLhgwYIG9T2oL4mPAs="
            },
            "amount": 489
        }
    ],
    "show_comments": [
        {
            "comment_id": 548814818515284,
            "create_time": "2019-12-27T01:45:02.310+0800",
            "owner": {
                "user_id": 551585858254,
                "name": "SOHO佳文",
                "avatar_url": "https://images.zsxq.com/FpODC11FFqBP7kKUm0WPzcHiz539?e=1590940799&token=kIxbL07-8jAj8w1n4s9zv64FuZZNEATmlU_Vm6zD:fpY-ewDCPcfCx2ZiP0Th-iiWG_0="
            },
            "text": "精品好货",
            "likes_count": 0,
            "rewards_count": 0
        },
        {
            "comment_id": 241184181228841,
            "create_time": "2019-12-27T03:35:19.627+0800",
            "owner": {
                "user_id": 241551221148511,
                "name": "苏泽",
                "avatar_url": "https://images.zsxq.com/FuaF4LZuGvc_7Wp-IkPoTc-ZCYTZ?e=1590940799&token=kIxbL07-8jAj8w1n4s9zv64FuZZNEATmlU_Vm6zD:Ll21wzVhk2Lt21JWmpIdaJfNknk="
            },
            "text": "受教了",
            "likes_count": 0,
            "rewards_count": 0
        },
        {
            "comment_id": 241181521455811,
            "create_time": "2019-12-27T14:23:08.704+0800",
            "owner": {
                "user_id": 8212415112,
                "name": "Jimi",
                "alias": "Jimi",
                "avatar_url": "https://images.zsxq.com/FiWv5yIogjugrkjGNdMOpLbJJQQg?e=1590940799&token=kIxbL07-8jAj8w1n4s9zv64FuZZNEATmlU_Vm6zD:3hf7dVV6u5P9ulK0iGgaBqJE7yo="
            },
            "text": "挺有感触的，尤其第14点，不过第四句不太懂，有没有人拓展一下。",
            "likes_count": 0,
            "rewards_count": 0,
            "replies_count": 4
        },
        {
            "comment_id": 548818258852514,
            "parent_comment_id": 241181521455811,
            "create_time": "2019-12-27T14:59:00.123+0800",
            "owner": {
                "user_id": 552158581144,
                "name": "亦仁",
                "alias": "亦仁",
                "avatar_url": "https://images.zsxq.com/Fn3NQqCN8nuGF86yZPXSbEsl0mb3?e=1590940799&token=kIxbL07-8jAj8w1n4s9zv64FuZZNEATmlU_Vm6zD:pfbNc8W3hS0oYG_hyXXh_rHMHuc=",
                "description": "一直在路上的创业者，「生财有术」星主，公众号「亦无所知」，个人微信号：yirenpro"
            },
            "text": "老板做决定，正确决定增加信任，错误决定减少信任。",
            "likes_count": 0,
            "rewards_count": 0,
            "repliee": {
                "user_id": 8212415112,
                "name": "Jimi",
                "alias": "Jimi",
                "avatar_url": "https://images.zsxq.com/FiWv5yIogjugrkjGNdMOpLbJJQQg?e=1590940799&token=kIxbL07-8jAj8w1n4s9zv64FuZZNEATmlU_Vm6zD:3hf7dVV6u5P9ulK0iGgaBqJE7yo="
            }
        },
        {
            "comment_id": 548818258882284,
            "parent_comment_id": 241181521455811,
            "create_time": "2019-12-27T15:10:45.276+0800",
            "owner": {
                "user_id": 8212415112,
                "name": "Jimi",
                "alias": "Jimi",
                "avatar_url": "https://images.zsxq.com/FiWv5yIogjugrkjGNdMOpLbJJQQg?e=1590940799&token=kIxbL07-8jAj8w1n4s9zv64FuZZNEATmlU_Vm6zD:3hf7dVV6u5P9ulK0iGgaBqJE7yo="
            },
            "text": "嗯嗯.14句理解哈，我好奇第四句那个，感觉比较突兀",
            "likes_count": 0,
            "rewards_count": 0,
            "repliee": {
                "user_id": 552158581144,
                "name": "亦仁",
                "alias": "亦仁",
                "avatar_url": "https://images.zsxq.com/Fn3NQqCN8nuGF86yZPXSbEsl0mb3?e=1590940799&token=kIxbL07-8jAj8w1n4s9zv64FuZZNEATmlU_Vm6zD:pfbNc8W3hS0oYG_hyXXh_rHMHuc=",
                "description": "一直在路上的创业者，「生财有术」星主，公众号「亦无所知」，个人微信号：yirenpro"
            }
        },
        {
            "comment_id": 548818245155844,
            "parent_comment_id": 241181521455811,
            "create_time": "2019-12-27T17:08:28.117+0800",
            "owner": {
                "user_id": 552158581144,
                "name": "亦仁",
                "alias": "亦仁",
                "avatar_url": "https://images.zsxq.com/Fn3NQqCN8nuGF86yZPXSbEsl0mb3?e=1590940799&token=kIxbL07-8jAj8w1n4s9zv64FuZZNEATmlU_Vm6zD:pfbNc8W3hS0oYG_hyXXh_rHMHuc=",
                "description": "一直在路上的创业者，「生财有术」星主，公众号「亦无所知」，个人微信号：yirenpro"
            },
            "text": "<e type=\"web\" href=\"https%3A%2F%2Ft.zsxq.com%2F7y7eiyR\" title=\"https%3A%2F%2Ft.zsxq.com%2F7y7eiyR\" />\n\n白一喵解释的挺好",
            "likes_count": 0,
            "rewards_count": 0,
            "repliee": {
                "user_id": 8212415112,
                "name": "Jimi",
                "alias": "Jimi",
                "avatar_url": "https://images.zsxq.com/FiWv5yIogjugrkjGNdMOpLbJJQQg?e=1590940799&token=kIxbL07-8jAj8w1n4s9zv64FuZZNEATmlU_Vm6zD:3hf7dVV6u5P9ulK0iGgaBqJE7yo="
            }
        },
        {
            "comment_id": 548818245514514,
            "parent_comment_id": 241181521455811,
            "create_time": "2019-12-27T17:28:27.774+0800",
            "owner": {
                "user_id": 8212415112,
                "name": "Jimi",
                "alias": "Jimi",
                "avatar_url": "https://images.zsxq.com/FiWv5yIogjugrkjGNdMOpLbJJQQg?e=1590940799&token=kIxbL07-8jAj8w1n4s9zv64FuZZNEATmlU_Vm6zD:3hf7dVV6u5P9ulK0iGgaBqJE7yo="
            },
            "text": "不错",
            "likes_count": 0,
            "rewards_count": 0,
            "repliee": {
                "user_id": 552158581144,
                "name": "亦仁",
                "alias": "亦仁",
                "avatar_url": "https://images.zsxq.com/Fn3NQqCN8nuGF86yZPXSbEsl0mb3?e=1590940799&token=kIxbL07-8jAj8w1n4s9zv64FuZZNEATmlU_Vm6zD:pfbNc8W3hS0oYG_hyXXh_rHMHuc=",
                "description": "一直在路上的创业者，「生财有术」星主，公众号「亦无所知」，个人微信号：yirenpro"
            }
        }
    ],
    "likes_count": 74,
    "rewards_count": 6,
    "comments_count": 7,
    "reading_count": 14081,
    "digested": true,
    "sticky": false,
    "create_time": "2019-12-26T23:44:06.588+0800",
    "modify_time": "2019-12-27T08:31:39.662+0800",
    "user_specific": {
        "liked": false,
        "subscribed": false
    }
}