{
    "topic_id": 544841155528154,
    "group": {
        "group_id": 1824528822,
        "name": "生财有术"
    },
    "type": "talk",
    "talk": {
        "owner": {
            "user_id": 552158581144,
            "name": "亦仁",
            "alias": "亦仁",
            "avatar_url": "https://images.zsxq.com/Fn3NQqCN8nuGF86yZPXSbEsl0mb3?e=1590940799&token=kIxbL07-8jAj8w1n4s9zv64FuZZNEATmlU_Vm6zD:pfbNc8W3hS0oYG_hyXXh_rHMHuc=",
            "description": "一直在路上的创业者，「生财有术」星主，公众号「亦无所知」，个人微信号：yirenpro"
        },
        "text": "有人用信息不对称，找到谷歌地球上一些图片做成抖音视频，勾引好奇心卖谷歌地球软件，刚才看一分钟内20-30笔订单，每笔订单39块，这个月3000多笔订单了，10万块到手。\n\n真的有人会傻到付费去买一个免费软件？ 真的有。\n\n任何一个我们以为众所周知的事情，都会至少有一亿人不知道，通常情况下，这个数字是十亿。"
    },
    "latest_likes": [
        {
            "create_time": "2020-04-08T09:47:08.404+0800",
            "owner": {
                "user_id": 228818141121,
                "name": "乔礼",
                "avatar_url": "https://images.zsxq.com/FgtcQFW3h1gwmVtFO6tyJdvav3Nz?e=1590940799&token=kIxbL07-8jAj8w1n4s9zv64FuZZNEATmlU_Vm6zD:gfHvOvAXNjEcTDrK-euHZ9ypgUY=",
                "number": 6902
            }
        },
        {
            "create_time": "2020-03-25T22:38:39.221+0800",
            "owner": {
                "user_id": 1181452442,
                "name": "雨亭之东",
                "avatar_url": "https://images.zsxq.com/Flp1-fvYdYb8NjmFl4oHO3zEpNHc?e=1590940799&token=kIxbL07-8jAj8w1n4s9zv64FuZZNEATmlU_Vm6zD:aPPmufuaj34jvqwD0H5DFUM2-fY=",
                "number": 2683
            }
        },
        {
            "create_time": "2020-03-13T12:26:32.424+0800",
            "owner": {
                "user_id": 552512114214,
                "name": "Alan",
                "avatar_url": "https://images.zsxq.com/FvjSuetTWQSx598UV2dF_xMyWFos?e=1590940799&token=kIxbL07-8jAj8w1n4s9zv64FuZZNEATmlU_Vm6zD:IExDP9PakyNWEk4_0QWsS9IEg6U=",
                "number": 1507
            }
        },
        {
            "create_time": "2020-03-12T18:26:00.540+0800",
            "owner": {
                "user_id": 552811888254,
                "name": "zone",
                "avatar_url": "https://images.zsxq.com/Fid_MGEQAGz_pS_LSn-aTv4NAqp4?e=1590940799&token=kIxbL07-8jAj8w1n4s9zv64FuZZNEATmlU_Vm6zD:8qG3xvuSjotO2NJIhM1AKc1GXoo=",
                "number": 4739
            }
        },
        {
            "create_time": "2020-03-12T17:15:27.992+0800",
            "owner": {
                "user_id": 548114415252824,
                "name": "要变强的小妍",
                "avatar_url": "https://images.zsxq.com/FuE0AQzwbGj9iSyUYx6KbyWJXHJj?e=1590940799&token=kIxbL07-8jAj8w1n4s9zv64FuZZNEATmlU_Vm6zD:nGhJMY2yMPsZHgYI-1CYA3UIUgo=",
                "number": 6594
            }
        },
        {
            "create_time": "2020-03-12T17:11:56.564+0800",
            "owner": {
                "user_id": 28845258544121,
                "name": "白杨seo",
                "avatar_url": "https://images.zsxq.com/FrpyjpBq0i5L3-YUUfEqMISgmGGE?e=1590940799&token=kIxbL07-8jAj8w1n4s9zv64FuZZNEATmlU_Vm6zD:crklZBvlJ2-Q7wx-bAqQBjhM0Z4=",
                "number": 3632
            }
        },
        {
            "create_time": "2020-02-19T13:17:10.647+0800",
            "owner": {
                "user_id": 88488844851822,
                "name": "两根头发又中分",
                "avatar_url": "https://images.zsxq.com/Fs584LMcSmlhTHUGK99xd2Z1SyR5?e=1590940799&token=kIxbL07-8jAj8w1n4s9zv64FuZZNEATmlU_Vm6zD:OtBshYn_3cNk_DcqyzpbPhw8qyk=",
                "number": 6150
            }
        },
        {
            "create_time": "2019-11-14T21:31:05.524+0800",
            "owner": {
                "user_id": 555541452844,
                "name": "瓜叔",
                "alias": "瓜叔",
                "avatar_url": "https://images.zsxq.com/FrzuX0d7nIgjA9JBwx9Bpiycg3F5?e=1590940799&token=kIxbL07-8jAj8w1n4s9zv64FuZZNEATmlU_Vm6zD:fN1nGfPFW3hs4Xl6qz3Ok6E-fM0=",
                "number": 2529
            }
        },
        {
            "create_time": "2019-11-04T14:46:44.630+0800",
            "owner": {
                "user_id": 48418518511418,
                "name": "Spider",
                "alias": "Spider",
                "avatar_url": "https://images.zsxq.com/Fl6i4lI9pn3GDILQEvy5QIYJfQfy?e=1590940799&token=kIxbL07-8jAj8w1n4s9zv64FuZZNEATmlU_Vm6zD:eaxxuZWNHBcyMnYdtglMWl3gabk=",
                "number": 6402
            }
        },
        {
            "create_time": "2019-10-04T16:03:28.988+0800",
            "owner": {
                "user_id": 222545184541,
                "name": "reed92deer",
                "avatar_url": "https://images.zsxq.com/FtH6_gJVAU-CxixNHE9ygAHMzMfa?e=1590940799&token=kIxbL07-8jAj8w1n4s9zv64FuZZNEATmlU_Vm6zD:L3Q25XUEO49vS0l12xf3JMixVaM=",
                "number": 6228
            }
        }
    ],
    "rewards": [
        {
            "create_time": "2020-03-13T09:06:58.946+0800",
            "owner": {
                "user_id": 28514445448211,
                "name": "伊迭",
                "avatar_url": "https://images.zsxq.com/FpND2B0L-xp28OUssH3Z6CHy4PZb?e=1590940799&token=kIxbL07-8jAj8w1n4s9zv64FuZZNEATmlU_Vm6zD:VZPQ75tnkJdbWg_hhqdWhzrTjrc="
            },
            "amount": 188
        },
        {
            "create_time": "2019-07-21T22:30:24.018+0800",
            "owner": {
                "user_id": 4184541448,
                "name": "杨正",
                "avatar_url": "https://images.zsxq.com/FpnW-7D_KN9AruAwff9raGxQie2O?e=1590940799&token=kIxbL07-8jAj8w1n4s9zv64FuZZNEATmlU_Vm6zD:Z4QnFrYKKhI6CeCUCMjEghbte2o="
            },
            "amount": 388
        }
    ],
    "show_comments": [
        {
            "comment_id": 421411558145418,
            "create_time": "2019-07-21T12:02:40.857+0800",
            "owner": {
                "user_id": 15284285488542,
                "name": "章真人",
                "avatar_url": "https://images.zsxq.com/FoDN8ZmmTtZ2qy5aFjXKzJ6qCJIW?e=1590940799&token=kIxbL07-8jAj8w1n4s9zv64FuZZNEATmlU_Vm6zD:zgmG9HN26qj7G4g0gQWRMCfleg0="
            },
            "text": "这种形式的业务真的还很多来",
            "likes_count": 0,
            "rewards_count": 0
        },
        {
            "comment_id": 241511228128441,
            "create_time": "2019-07-21T12:30:58.665+0800",
            "owner": {
                "user_id": 4288858848,
                "name": "Michael",
                "avatar_url": "https://images.zsxq.com/Fsr95dILTHyl79v5I-_X0LUqQdvt?e=1590940799&token=kIxbL07-8jAj8w1n4s9zv64FuZZNEATmlU_Vm6zD:Ujhfca4qgldH0Cano7vdAGZoXEI="
            },
            "text": "实际上他们的工作是有价值的，他们提供了信息价值，让这些人知道有这样一个东西，还成功种草，毕竟人的认知都有局限，换成是我们，也许互联网圈的很难被忽悠，换其他的就不一定了。生意的本质很大程度也是信息不对称的利用。",
            "likes_count": 1,
            "rewards_count": 0,
            "replies_count": 1
        },
        {
            "comment_id": 548288551858214,
            "parent_comment_id": 241511228128441,
            "create_time": "2019-07-21T12:39:55.615+0800",
            "owner": {
                "user_id": 552158581144,
                "name": "亦仁",
                "alias": "亦仁",
                "avatar_url": "https://images.zsxq.com/Fn3NQqCN8nuGF86yZPXSbEsl0mb3?e=1590940799&token=kIxbL07-8jAj8w1n4s9zv64FuZZNEATmlU_Vm6zD:pfbNc8W3hS0oYG_hyXXh_rHMHuc=",
                "description": "一直在路上的创业者，「生财有术」星主，公众号「亦无所知」，个人微信号：yirenpro"
            },
            "text": "嗯 有价值，拉平信息不对称就是有价值。",
            "likes_count": 0,
            "rewards_count": 0,
            "repliee": {
                "user_id": 4288858848,
                "name": "Michael",
                "avatar_url": "https://images.zsxq.com/Fsr95dILTHyl79v5I-_X0LUqQdvt?e=1590940799&token=kIxbL07-8jAj8w1n4s9zv64FuZZNEATmlU_Vm6zD:Ujhfca4qgldH0Cano7vdAGZoXEI="
            }
        },
        {
            "comment_id": 841511221518512,
            "create_time": "2019-07-21T15:22:27.434+0800",
            "owner": {
                "user_id": 225812814821,
                "name": "渊杰",
                "avatar_url": "https://images.zsxq.com/FqijMd77_2R-m87UnuPl_9_hoS_O?e=1590940799&token=kIxbL07-8jAj8w1n4s9zv64FuZZNEATmlU_Vm6zD:-Tb_FWI3FNqwtoV_gI7G2n9Ln50="
            },
            "text": "视频做得好？",
            "likes_count": 0,
            "rewards_count": 0
        },
        {
            "comment_id": 118288448554552,
            "create_time": "2019-07-21T15:59:03.648+0800",
            "owner": {
                "user_id": 142584288282,
                "name": "边城浪子",
                "avatar_url": "https://images.zsxq.com/Fv75C0ErsqJoVkdC3_FDCG-MswM6?e=1590940799&token=kIxbL07-8jAj8w1n4s9zv64FuZZNEATmlU_Vm6zD:_k-78DMDolc7vQou50YXVpAjo2w="
            },
            "text": "求抖音地址，我要学习",
            "likes_count": 0,
            "rewards_count": 0,
            "replies_count": 1
        },
        {
            "comment_id": 548288558514454,
            "create_time": "2019-07-21T16:41:53.270+0800",
            "owner": {
                "user_id": 48828525881428,
                "name": "小白",
                "avatar_url": "https://images.zsxq.com/Fs7gNHsLT7hDc3m93bPb_6sjcBHl?e=1590940799&token=kIxbL07-8jAj8w1n4s9zv64FuZZNEATmlU_Vm6zD:sSvM-UPrWV_dSHNbpjRbMNcGK0U="
            },
            "text": "求抖音地址",
            "likes_count": 0,
            "rewards_count": 0
        },
        {
            "comment_id": 421411551225188,
            "parent_comment_id": 118288448554552,
            "create_time": "2019-07-21T17:52:27.434+0800",
            "owner": {
                "user_id": 552158581144,
                "name": "亦仁",
                "alias": "亦仁",
                "avatar_url": "https://images.zsxq.com/Fn3NQqCN8nuGF86yZPXSbEsl0mb3?e=1590940799&token=kIxbL07-8jAj8w1n4s9zv64FuZZNEATmlU_Vm6zD:pfbNc8W3hS0oYG_hyXXh_rHMHuc=",
                "description": "一直在路上的创业者，「生财有术」星主，公众号「亦无所知」，个人微信号：yirenpro"
            },
            "text": "",
            "likes_count": 0,
            "rewards_count": 0,
            "images": [
                {
                    "image_id": 422141144814848,
                    "type": "jpg",
                    "thumbnail": {
                        "url": "https://images.zsxq.com/Fsi1XF7IBxEyIjKqT6_kRfWCn_ao?imageMogr2/auto-orient/thumbnail/320x/format/jpg/blur/1x0/quality/75&e=1590940799&token=kIxbL07-8jAj8w1n4s9zv64FuZZNEATmlU_Vm6zD:dWAdeJH7AZysUcGQnKUhgAa7A8o=",
                        "width": 320,
                        "height": 569
                    },
                    "large": {
                        "url": "https://images.zsxq.com/Fsi1XF7IBxEyIjKqT6_kRfWCn_ao?imageMogr2/auto-orient/thumbnail/800x/format/jpg/blur/1x0/quality/75&e=1590940799&token=kIxbL07-8jAj8w1n4s9zv64FuZZNEATmlU_Vm6zD:O7IAGHEa8Y9htFsGpxdNxYC7HGs=",
                        "width": 800,
                        "height": 1422
                    },
                    "original": {
                        "url": "https://images.zsxq.com/Fsi1XF7IBxEyIjKqT6_kRfWCn_ao?e=1590940799&token=kIxbL07-8jAj8w1n4s9zv64FuZZNEATmlU_Vm6zD:AwU-SKhLZUBlMrL8mXGSSB-Hnd4=",
                        "width": 1080,
                        "height": 1920,
                        "size": 462117
                    }
                }
            ],
            "repliee": {
                "user_id": 142584288282,
                "name": "边城浪子",
                "avatar_url": "https://images.zsxq.com/Fv75C0ErsqJoVkdC3_FDCG-MswM6?e=1590940799&token=kIxbL07-8jAj8w1n4s9zv64FuZZNEATmlU_Vm6zD:_k-78DMDolc7vQou50YXVpAjo2w="
            }
        },
        {
            "comment_id": 841511245825182,
            "create_time": "2019-07-21T20:08:17.348+0800",
            "owner": {
                "user_id": 51448482518884,
                "name": "白江",
                "alias": "莱特",
                "avatar_url": "https://images.zsxq.com/FhZEEy_ZXZfVAz47KU5Qz1tla9nu?e=1590940799&token=kIxbL07-8jAj8w1n4s9zv64FuZZNEATmlU_Vm6zD:5yoGnDqTXBzZpw5QVOXYJ-Xr588="
            },
            "text": "查了一番，几个线索：\n咸鱼以前有人卖；知乎上有提问怎么获取该软件",
            "likes_count": 0,
            "rewards_count": 0
        }
    ],
    "likes_count": 114,
    "rewards_count": 2,
    "comments_count": 19,
    "reading_count": 31805,
    "digested": true,
    "sticky": false,
    "create_time": "2019-07-21T12:01:05.181+0800",
    "modify_time": "2019-07-21T12:14:20.157+0800",
    "user_specific": {
        "liked": false,
        "subscribed": false
    }
}