{
    "topic_id": 824481555452,
    "group": {
        "group_id": 1824528822,
        "name": "生财有术"
    },
    "type": "talk",
    "talk": {
        "owner": {
            "user_id": 552158581144,
            "name": "亦仁",
            "alias": "亦仁",
            "avatar_url": "https://images.zsxq.com/Fn3NQqCN8nuGF86yZPXSbEsl0mb3?e=1590940799&token=kIxbL07-8jAj8w1n4s9zv64FuZZNEATmlU_Vm6zD:pfbNc8W3hS0oYG_hyXXh_rHMHuc=",
            "description": "一直在路上的创业者，「生财有术」星主，公众号「亦无所知」，个人微信号：yirenpro"
        },
        "text": "<e type=\"hashtag\" hid=\"8458121242\" title=\"#这叫执行力#\" />",
        "images": [
            {
                "image_id": 452541542118,
                "type": "jpg",
                "thumbnail": {
                    "url": "https://images.zsxq.com/FjJMsdV7T0JxrpeZz5ciOvfFV9a8?imageMogr2/auto-orient/thumbnail/540x/format/jpg/blur/1x0/quality/75&e=1590940799&token=kIxbL07-8jAj8w1n4s9zv64FuZZNEATmlU_Vm6zD:Px3Brzdi1GgfJ4aUTLHDPsDN6dU=",
                    "width": 540,
                    "height": 960
                },
                "large": {
                    "url": "https://images.zsxq.com/FjJMsdV7T0JxrpeZz5ciOvfFV9a8?imageMogr2/auto-orient/thumbnail/800x/format/jpg/blur/1x0/quality/75&e=1590940799&token=kIxbL07-8jAj8w1n4s9zv64FuZZNEATmlU_Vm6zD:rqLLfu1evxgdQWbqixC-sjiQ_a4=",
                    "width": 800,
                    "height": 1422
                },
                "original": {
                    "url": "https://images.zsxq.com/FjJMsdV7T0JxrpeZz5ciOvfFV9a8?e=1590940799&token=kIxbL07-8jAj8w1n4s9zv64FuZZNEATmlU_Vm6zD:uXNY7aCaZtG1DAQxSBNGrOuJ4G8=",
                    "width": 1080,
                    "height": 1920,
                    "size": 349277
                }
            }
        ]
    },
    "latest_likes": [
        {
            "create_time": "2020-03-26T21:53:49.964+0800",
            "owner": {
                "user_id": 48812588225218,
                "name": "傅超人",
                "avatar_url": "https://images.zsxq.com/Fsj8n5BCabzlDRXyFu1MmjMJ4nlk?e=1590940799&token=kIxbL07-8jAj8w1n4s9zv64FuZZNEATmlU_Vm6zD:XHuYQZhhXQsSDuvRx25zvl1PklY=",
                "number": 2824
            }
        },
        {
            "create_time": "2019-07-30T17:22:14.378+0800",
            "owner": {
                "user_id": 552514451124,
                "name": "于洋",
                "avatar_url": "https://images.zsxq.com/Frjqth-Vh5fOTjLrBhibEraLffou?e=1590940799&token=kIxbL07-8jAj8w1n4s9zv64FuZZNEATmlU_Vm6zD:ze9GN5FClP6ArhmXeFK86HSS5tk=",
                "number": 2877
            }
        },
        {
            "create_time": "2019-05-30T23:23:17.975+0800",
            "owner": {
                "user_id": 422255418541218,
                "name": "百里登风",
                "avatar_url": "https://images.zsxq.com/FnbBOoWkT0qqlnnr9P7hAeXxqZVu?e=1590940799&token=kIxbL07-8jAj8w1n4s9zv64FuZZNEATmlU_Vm6zD:hMRULgl0tn3pp7uxshHm0R-hjFM=",
                "number": 5690
            }
        },
        {
            "create_time": "2019-05-17T15:22:19.514+0800",
            "owner": {
                "user_id": 88885412282252,
                "name": "扇扇",
                "avatar_url": "https://images.zsxq.com/FhiChtUV3LlmPRUPz1Qcz4Ryq8Su?e=1590940799&token=kIxbL07-8jAj8w1n4s9zv64FuZZNEATmlU_Vm6zD:ozDMv-VNM_dM4UIrX7kqIGU_xuY=",
                "number": 3289
            }
        },
        {
            "create_time": "2018-11-18T19:31:18.956+0800",
            "owner": {
                "user_id": 825185842552,
                "name": "吴陆柒",
                "avatar_url": "https://images.zsxq.com/Fg6A2FLq3CyJ-dE_nOjqruvjwc9K?e=1590940799&token=kIxbL07-8jAj8w1n4s9zv64FuZZNEATmlU_Vm6zD:pgLm8rCatpqcaWRAzysDwfXsOYE=",
                "number": 1621
            }
        },
        {
            "create_time": "2017-04-30T16:56:19.052+0800",
            "owner": {
                "user_id": 5458844584,
                "name": "tony",
                "avatar_url": "https://images.zsxq.com/FgGtHkhyMp5Jp0ruteuRm2z9aFyg?e=1590940799&token=kIxbL07-8jAj8w1n4s9zv64FuZZNEATmlU_Vm6zD:C8YIvgblxMZK0RvdSj5EiiHeHOM=",
                "number": 850
            }
        },
        {
            "create_time": "2017-04-29T08:40:47.149+0800",
            "owner": {
                "user_id": 228588525581,
                "name": "赵祺",
                "avatar_url": "https://images.zsxq.com/Fll9FSJhfDQ_GleXgxPYZCvoanSS?e=1590940799&token=kIxbL07-8jAj8w1n4s9zv64FuZZNEATmlU_Vm6zD:Z9hqASw3VLs1grInbdV9edwqfR0=",
                "number": 609
            }
        },
        {
            "create_time": "2017-04-29T07:39:48.636+0800",
            "owner": {
                "user_id": 828214481252,
                "name": "中雨",
                "avatar_url": "https://images.zsxq.com/FoY3OFZp9ZcP2Lm2ndcwIYFClsG5?e=1590940799&token=kIxbL07-8jAj8w1n4s9zv64FuZZNEATmlU_Vm6zD:t2dZsf_zeIsx2k3a_AN42EyGCg8=",
                "number": 832
            }
        },
        {
            "create_time": "2017-04-28T20:34:32.724+0800",
            "owner": {
                "user_id": 825844448222,
                "name": "乔",
                "avatar_url": "https://images.zsxq.com/FgIm1OyygJ1YLIEpuaLN2UghF7xK?e=1590940799&token=kIxbL07-8jAj8w1n4s9zv64FuZZNEATmlU_Vm6zD:TlbHs0SfuLMukCMl53wY_gRi52c=",
                "number": 380
            }
        },
        {
            "create_time": "2017-04-28T17:47:12.503+0800",
            "owner": {
                "user_id": 827828127,
                "name": "wulujia",
                "avatar_url": "https://images.zsxq.com/FvMs_TiGOIa6-0xoJet3wAXslVqD?e=1590940799&token=kIxbL07-8jAj8w1n4s9zv64FuZZNEATmlU_Vm6zD:jXyHUfNUOvC5TFfiCbUhbxUarXM=",
                "description": "知识星球创始人",
                "number": 56
            }
        }
    ],
    "show_comments": [
        {
            "comment_id": 824282551222,
            "create_time": "2017-04-27T16:38:08.514+0800",
            "owner": {
                "user_id": 721441521,
                "name": "汤tang",
                "avatar_url": "https://images.zsxq.com/FqTuACjTb7eiKBYSWOba3XzeJmtH?e=1590940799&token=kIxbL07-8jAj8w1n4s9zv64FuZZNEATmlU_Vm6zD:7cRxQy9SSV6eGYv7rpX-nbYrRT0="
            },
            "text": "给这哥们点赞去",
            "likes_count": 0,
            "rewards_count": 0
        },
        {
            "comment_id": 824282551122,
            "create_time": "2017-04-27T16:40:24.690+0800",
            "owner": {
                "user_id": 721441521,
                "name": "汤tang",
                "avatar_url": "https://images.zsxq.com/FqTuACjTb7eiKBYSWOba3XzeJmtH?e=1590940799&token=kIxbL07-8jAj8w1n4s9zv64FuZZNEATmlU_Vm6zD:7cRxQy9SSV6eGYv7rpX-nbYrRT0="
            },
            "text": "<e type=\"web\" href=\"https%3A%2F%2Fwww.zhihu.com%2Fquestion%2F20840874%2Fanswer%2F161442181\" title=\"%E5%93%AA%E4%BA%9B%E4%B8%9C%E8%A5%BF%E4%B9%B0%E4%BA%86%E4%B9%8B%E5%90%8E%EF%BC%8C%E4%BC%9A%E8%AE%A9%E4%BA%BA%E5%9B%A0%E7%94%9F%E6%B4%BB%E8%B4%A8%E9%87%8F%E5%92%8C%E5%B9%B8%E7%A6%8F%E6%84%9F%E6%8F%90%E5%8D%87%E8%80%8C%E6%84%9F%E8%A7%89%E7%9B%B8%E8%A7%81%E6%81%A8%E6%99%9A%EF%BC%9F+-+%E7%9F%A5%E4%B9%8E\" cache=\"http%3A%2F%2Fcache.xiaomiquan.com%2F201704%2F26c036f5f29f4edc06511bf6e844385e3f6255668fa96e83d70d27a47121bbea\" />",
            "likes_count": 0,
            "rewards_count": 0
        },
        {
            "comment_id": 824282588552,
            "create_time": "2017-04-27T16:43:23.150+0800",
            "owner": {
                "user_id": 721441521,
                "name": "汤tang",
                "avatar_url": "https://images.zsxq.com/FqTuACjTb7eiKBYSWOba3XzeJmtH?e=1590940799&token=kIxbL07-8jAj8w1n4s9zv64FuZZNEATmlU_Vm6zD:7cRxQy9SSV6eGYv7rpX-nbYrRT0="
            },
            "text": "说起来平台做大了，如何快速找人就是一个问题，腾讯的产品就很好，qq号微信号。知乎这简直反例。",
            "likes_count": 0,
            "rewards_count": 0,
            "images": [
                {
                    "image_id": 824251241452,
                    "type": "png",
                    "thumbnail": {
                        "url": "https://images.zsxq.com/FtyAaFFS_PcrcTXFTBFEvwsUgi4E?imageMogr2/auto-orient/thumbnail/320x/format/jpg/blur/1x0/quality/75&e=1590940799&token=kIxbL07-8jAj8w1n4s9zv64FuZZNEATmlU_Vm6zD:BWvQ-x0bD_5VmwN6UHtnB_kkhBk=",
                        "width": 320,
                        "height": 568
                    },
                    "large": {
                        "url": "https://images.zsxq.com/FtyAaFFS_PcrcTXFTBFEvwsUgi4E?e=1590940799&token=kIxbL07-8jAj8w1n4s9zv64FuZZNEATmlU_Vm6zD:u7GR0jnJdVoNYJQq-KB6VPh22fc=",
                        "width": 640,
                        "height": 1136
                    }
                }
            ],
            "replies_count": 1
        },
        {
            "comment_id": 554515211214,
            "create_time": "2017-04-27T16:44:02.692+0800",
            "owner": {
                "user_id": 228212841281,
                "name": "胡克",
                "avatar_url": "https://images.zsxq.com/FqP-NQMdhdbrgaGDyzD4fjwJJGpz?e=1590940799&token=kIxbL07-8jAj8w1n4s9zv64FuZZNEATmlU_Vm6zD:rxO4L-ZLmS4X0ecYPBYNP0c_ypk="
            },
            "text": "记得有个哥们说五一后做的， 是不是不用做了",
            "likes_count": 0,
            "rewards_count": 0
        },
        {
            "comment_id": 224282588821,
            "create_time": "2017-04-27T16:45:25.412+0800",
            "owner": {
                "user_id": 4254482558,
                "name": "佳境",
                "avatar_url": "https://images.zsxq.com/Fkqzn69V-jtcFSKD4VlhnEv0N-Y9?e=1590940799&token=kIxbL07-8jAj8w1n4s9zv64FuZZNEATmlU_Vm6zD:izlRvYTClzvlCcS7vYSBjU-KUDM="
            },
            "text": "埋没在茫茫跟帖中了  翻了半天找不到这个答案",
            "likes_count": 0,
            "rewards_count": 0
        },
        {
            "comment_id": 141454255452,
            "create_time": "2017-04-27T16:46:23.162+0800",
            "owner": {
                "user_id": 4254482558,
                "name": "佳境",
                "avatar_url": "https://images.zsxq.com/Fkqzn69V-jtcFSKD4VlhnEv0N-Y9?e=1590940799&token=kIxbL07-8jAj8w1n4s9zv64FuZZNEATmlU_Vm6zD:izlRvYTClzvlCcS7vYSBjU-KUDM="
            },
            "text": "有个直接丢淘宝客链接的找到了",
            "likes_count": 0,
            "rewards_count": 0
        },
        {
            "comment_id": 824282588242,
            "create_time": "2017-04-27T16:47:07.083+0800",
            "owner": {
                "user_id": 1142548552,
                "name": "Amos",
                "alias": "Amos",
                "avatar_url": "https://images.zsxq.com/FuprT0lazszsHGKPNJi3gf4qmkmQ?e=1590940799&token=kIxbL07-8jAj8w1n4s9zv64FuZZNEATmlU_Vm6zD:NhQtq05o3QrmNC-vXg9Ff9Ri3gc="
            },
            "text": "后续有新的进度和数据，亦仁能不能分享下…想体验下亲眼看到一个项目被孵出来的过程",
            "likes_count": 0,
            "rewards_count": 0
        },
        {
            "comment_id": 141454255142,
            "parent_comment_id": 824282588552,
            "create_time": "2017-04-27T16:48:00.194+0800",
            "owner": {
                "user_id": 1142548552,
                "name": "Amos",
                "alias": "Amos",
                "avatar_url": "https://images.zsxq.com/FuprT0lazszsHGKPNJi3gf4qmkmQ?e=1590940799&token=kIxbL07-8jAj8w1n4s9zv64FuZZNEATmlU_Vm6zD:NhQtq05o3QrmNC-vXg9Ff9Ri3gc="
            },
            "text": "还好你发了链接出来，我都找不到",
            "likes_count": 0,
            "rewards_count": 0,
            "repliee": {
                "user_id": 721441521,
                "name": "汤tang",
                "avatar_url": "https://images.zsxq.com/FqTuACjTb7eiKBYSWOba3XzeJmtH?e=1590940799&token=kIxbL07-8jAj8w1n4s9zv64FuZZNEATmlU_Vm6zD:7cRxQy9SSV6eGYv7rpX-nbYrRT0="
            }
        }
    ],
    "likes_count": 31,
    "rewards_count": 0,
    "comments_count": 15,
    "reading_count": 1943,
    "digested": true,
    "sticky": false,
    "create_time": "2017-04-27T16:36:24.414+0800",
    "user_specific": {
        "liked": false,
        "subscribed": false
    }
}