{
    "topic_id": 844118528452512,
    "group": {
        "group_id": 1824528822,
        "name": "生财有术"
    },
    "type": "talk",
    "talk": {
        "owner": {
            "user_id": 88821825445242,
            "name": "吴都",
            "avatar_url": "https://images.zsxq.com/FrT_S0TjWQlZK1w8iGGtqRxjYaTH?e=1590940799&token=kIxbL07-8jAj8w1n4s9zv64FuZZNEATmlU_Vm6zD:GSHH9u5Ot0wYawCPEomMrLrWD7I="
        },
        "text": "一个迷之自信的人\n\n总是碰到一些迷之自信的人，主要体现在：\n当听到某个人或者某企业的经验分享时，会说，这有什么啊，他们说的做的我都知道啊，他们的关键突破点我也早就想到过啊，他们没什么厉害的，他们能做的我也能做到。我没有像他们那样成功无非就是因为我在公司没有话语权或者我没有拿到一大笔投资等等……\n\n平时遇到这些人，我也是置之不理。遇到特别不喜欢的，甚至还会真诚地附和夸两句，有句话不是说，对待SB的方式就是不停地称赞他，让他成长为一个大SB吗。\n\n直到我发现我公司也出现了这样的不知天高地厚，不知道自己不知道的人的存在。于是，我觉得我应该认认真真的规劝一下这些人，要有敬畏之心。\n\n这些迷之自信的人，总认为别人成功的要素，方法他都想到了。他只是客观条件限制而没去做而已，所以认真做事并且做成了的人也没有什么大不了的本事。\n\n然而真相是什么呢？\n真相是，在做决策中，厉害的人在纷杂的业务线中可能找到适合的10个突破口，然后在远胜于你的经验基础上，旁求博考，最终选择了他认为最有效率的一条，开始行动。\n\n这个过程中他曾经积累的经验可能是你的10倍，他为了做出最后决策所做的各种考证，思考可能是你的10倍。\n\n然后，他会快速执行，落地，推进。这个过程中，他付出的努力可能是你的10倍。\n\n如果碰到没有成功经验借鉴，超出自己认识范围的时候，他翻阅的各种书籍可能是你的10倍。\n\n任务推进过程中会出现迅速调整执行方式，甚至会快速推翻前一个决策，重新来做，他会遭受外部质疑以及自我否定，在这样的困局中他需要做出适当的自我心理建设。在这个时候他付出的心力可能是你的10倍。\n\n这样一个从决策到执行完毕的过程中，他获得的经验值又是你的10倍\n \n你以为这样就足够了吗？no，远远不够，这只是一个决策而已，一个企业一个人最终能取得一些成绩，是一系列的决策，而且是一系列正确的决策，持续的正确的决策，（不正确的决策会迅速被调整替换掉）。那么在这样一系列的决策执行过程中，你做的那部分（想到一两个观点）仅仅是人家的万分之一而已。\n \n而因为在你脑海中曾经出现过的100个念头，其中中正好有一两个念头与人家最初的决策点有重合，或者人家用的路径、方法或者方向曾经与你在网上了解的那些信息一致，你就误以为自己就是那个厉害的人，这种认知太可怕了。\n\n要知道在信息爆炸，知识付费遍地的今天，你与成功人士有一两个想法或观点的重合简直就是一个100%概率事件。\n\n你只见了冰山一角，水下的庞大部分你根本没曾窥见一二。\n这就是为什么说，想与做有巨大的鸿沟。\n迷之自信的人，永远是迷之自信，殊不知，在想与做之间，他与厉害的人之间其实早就是云泥之别了，因为持续的做与想之间能力的增长是指数级的增长。"
    },
    "latest_likes": [
        {
            "create_time": "2020-04-07T22:24:22.387+0800",
            "owner": {
                "user_id": 228818141121,
                "name": "乔礼",
                "avatar_url": "https://images.zsxq.com/FgtcQFW3h1gwmVtFO6tyJdvav3Nz?e=1590940799&token=kIxbL07-8jAj8w1n4s9zv64FuZZNEATmlU_Vm6zD:gfHvOvAXNjEcTDrK-euHZ9ypgUY=",
                "number": 6902
            }
        },
        {
            "create_time": "2019-11-26T11:36:14.790+0800",
            "owner": {
                "user_id": 544441141851224,
                "name": "盗坤",
                "avatar_url": "https://images.zsxq.com/FqbJOHmIe6DiSiUSwJOs_pXFPlNc?e=1590940799&token=kIxbL07-8jAj8w1n4s9zv64FuZZNEATmlU_Vm6zD:o62jNb--xBs9DwEEh1OchrkhcNs=",
                "number": 6261
            }
        },
        {
            "create_time": "2019-10-20T21:41:20.981+0800",
            "owner": {
                "user_id": 118212112222112,
                "name": "666",
                "avatar_url": "https://file.zsxq.com/wx_avatar.jpeg",
                "number": 6262
            }
        },
        {
            "create_time": "2019-08-13T18:46:50.711+0800",
            "owner": {
                "user_id": 828214852452,
                "name": "广陵散客",
                "alias": "崔承栋",
                "avatar_url": "https://images.zsxq.com/FhHwyzJ1zWtbA52TDvzwCGBRJnC4?e=1590940799&token=kIxbL07-8jAj8w1n4s9zv64FuZZNEATmlU_Vm6zD:e7ehlRo8Z_YdQQ4qDjK2nAmYZoA=",
                "number": 1439
            }
        },
        {
            "create_time": "2019-08-11T21:48:15.063+0800",
            "owner": {
                "user_id": 48851118242488,
                "name": "镌刻时光",
                "avatar_url": "https://images.zsxq.com/FmGd8TY11sEfK7Cfnbto9afi5fLl?e=1590940799&token=kIxbL07-8jAj8w1n4s9zv64FuZZNEATmlU_Vm6zD:vY-jeZobLLQLqxwDOg6BJReUoXE=",
                "number": 2555
            }
        },
        {
            "create_time": "2019-08-11T00:49:58.733+0800",
            "owner": {
                "user_id": 158452554282,
                "name": "Philipp Ma",
                "avatar_url": "https://images.zsxq.com/Fi9ou2ShvE4g7lVUJ0LLeI9Y-rl4?e=1590940799&token=kIxbL07-8jAj8w1n4s9zv64FuZZNEATmlU_Vm6zD:YW_fMLuJYAuEdjAS2SIbqxisa-s=",
                "number": 3714
            }
        },
        {
            "create_time": "2019-08-09T01:23:41.447+0800",
            "owner": {
                "user_id": 28452225558851,
                "name": "陈超",
                "alias": "markecc超",
                "avatar_url": "https://images.zsxq.com/FscnepyKYQnbqEhk3nCyksRTHhw4?e=1590940799&token=kIxbL07-8jAj8w1n4s9zv64FuZZNEATmlU_Vm6zD:YSYdx6LwsxxpMa7hKf0RPqCgEjI=",
                "number": 3314
            }
        },
        {
            "create_time": "2019-08-08T07:22:24.193+0800",
            "owner": {
                "user_id": 225225151281,
                "name": "韩龙",
                "alias": "海贼王",
                "avatar_url": "https://images.zsxq.com/Fs82wyy8wwV7m2v6NGWYkqxnMG6E?e=1590940799&token=kIxbL07-8jAj8w1n4s9zv64FuZZNEATmlU_Vm6zD:2vgjVPHYn757g7lb8OamJ5ECN6I=",
                "number": 102
            }
        },
        {
            "create_time": "2019-08-06T12:33:27.716+0800",
            "owner": {
                "user_id": 555522285284,
                "name": "Anna",
                "avatar_url": "https://images.zsxq.com/Fiehls6BOlCRJE1a_ZB-mOZEZg3Y?e=1590940799&token=kIxbL07-8jAj8w1n4s9zv64FuZZNEATmlU_Vm6zD:n6F1GaoKBNTqK2zhvhjz5GWlF8s=",
                "number": 4265
            }
        },
        {
            "create_time": "2019-08-05T21:18:46.617+0800",
            "owner": {
                "user_id": 88242442548442,
                "name": "贤仔",
                "avatar_url": "https://images.zsxq.com/FkGnr4vUCEa578pwXqZhA1yMDOzd?e=1590940799&token=kIxbL07-8jAj8w1n4s9zv64FuZZNEATmlU_Vm6zD:KImhPtYaebBAhNEVWC3yOVb6Wys=",
                "number": 5816
            }
        }
    ],
    "rewards": [
        {
            "create_time": "2019-08-03T18:55:30.089+0800",
            "owner": {
                "user_id": 552158581144,
                "name": "亦仁",
                "alias": "亦仁",
                "avatar_url": "https://images.zsxq.com/Fn3NQqCN8nuGF86yZPXSbEsl0mb3?e=1590940799&token=kIxbL07-8jAj8w1n4s9zv64FuZZNEATmlU_Vm6zD:pfbNc8W3hS0oYG_hyXXh_rHMHuc=",
                "description": "一直在路上的创业者，「生财有术」星主，公众号「亦无所知」，个人微信号：yirenpro"
            },
            "amount": 1900
        },
        {
            "create_time": "2019-11-21T17:04:29.287+0800",
            "owner": {
                "user_id": 51541512414524,
                "name": "windle",
                "avatar_url": "https://images.zsxq.com/FjLbVwgDYQZ8p57h7srz71pTgW0K?e=1590940799&token=kIxbL07-8jAj8w1n4s9zv64FuZZNEATmlU_Vm6zD:X32nxjwhkBZkVunoPy2qtLjMUHU="
            },
            "amount": 80
        },
        {
            "create_time": "2019-08-05T00:12:02.132+0800",
            "owner": {
                "user_id": 511211554,
                "name": "shaojbg",
                "avatar_url": "https://images.zsxq.com/FkjVhWuUGHreXe2PJBFoOdQ-ZcXA?e=1590940799&token=kIxbL07-8jAj8w1n4s9zv64FuZZNEATmlU_Vm6zD:mPJkSh1zMo4bCAn5d_-gVDwAaCY="
            },
            "amount": 422
        },
        {
            "create_time": "2019-08-04T01:34:35.080+0800",
            "owner": {
                "user_id": 2212852121,
                "name": "Kosan",
                "avatar_url": "https://images.zsxq.com/FlcmF02R9UlDg8w3-H9qb2TH0CA2?e=1590940799&token=kIxbL07-8jAj8w1n4s9zv64FuZZNEATmlU_Vm6zD:JRp8W8qOSiBt8UJOVRiY3ZlBaEk="
            },
            "amount": 168
        },
        {
            "create_time": "2019-08-04T00:50:43.338+0800",
            "owner": {
                "user_id": 881251255842,
                "name": "瓶子",
                "avatar_url": "https://images.zsxq.com/FgqJ47k7-h0Axackmf01v5cLAXfZ?e=1590940799&token=kIxbL07-8jAj8w1n4s9zv64FuZZNEATmlU_Vm6zD:OElOZBAPtrxJca3vjYmSHzqx63o="
            },
            "amount": 121
        },
        {
            "create_time": "2019-08-03T19:12:03.630+0800",
            "owner": {
                "user_id": 551525442214,
                "name": "肖烨",
                "avatar_url": "https://images.zsxq.com/Fstk6IvxhBjJMbSwEKZGolMrGljI?e=1590940799&token=kIxbL07-8jAj8w1n4s9zv64FuZZNEATmlU_Vm6zD:NprH1JNAnZYDHaes1uujISNZywM="
            },
            "amount": 268
        }
    ],
    "show_comments": [
        {
            "comment_id": 241858542481821,
            "create_time": "2019-08-03T18:51:32.722+0800",
            "owner": {
                "user_id": 551525442214,
                "name": "肖烨",
                "avatar_url": "https://images.zsxq.com/Fstk6IvxhBjJMbSwEKZGolMrGljI?e=1590940799&token=kIxbL07-8jAj8w1n4s9zv64FuZZNEATmlU_Vm6zD:NprH1JNAnZYDHaes1uujISNZywM="
            },
            "text": "这个是自己的感悟还是在哪看到的？写的特别好",
            "likes_count": 0,
            "rewards_count": 0,
            "replies_count": 1
        },
        {
            "comment_id": 241858542424811,
            "parent_comment_id": 241858542481821,
            "create_time": "2019-08-03T19:02:37.490+0800",
            "owner": {
                "user_id": 88821825445242,
                "name": "吴都",
                "avatar_url": "https://images.zsxq.com/FrT_S0TjWQlZK1w8iGGtqRxjYaTH?e=1590940799&token=kIxbL07-8jAj8w1n4s9zv64FuZZNEATmlU_Vm6zD:GSHH9u5Ot0wYawCPEomMrLrWD7I="
            },
            "text": "原创[呲牙]",
            "likes_count": 0,
            "rewards_count": 0,
            "repliee": {
                "user_id": 551525442214,
                "name": "肖烨",
                "avatar_url": "https://images.zsxq.com/Fstk6IvxhBjJMbSwEKZGolMrGljI?e=1590940799&token=kIxbL07-8jAj8w1n4s9zv64FuZZNEATmlU_Vm6zD:NprH1JNAnZYDHaes1uujISNZywM="
            }
        },
        {
            "comment_id": 118525218818482,
            "create_time": "2019-08-03T21:27:32.149+0800",
            "owner": {
                "user_id": 48882248144228,
                "name": "meek",
                "avatar_url": "https://images.zsxq.com/FqwQF8BLhyJI-N2iGD_Jv7GkjSwR?e=1590940799&token=kIxbL07-8jAj8w1n4s9zv64FuZZNEATmlU_Vm6zD:rRfqfSnStZgESVnOXbRiItGlyow="
            },
            "text": "拜读了，写的真好",
            "likes_count": 0,
            "rewards_count": 0
        },
        {
            "comment_id": 548121282125424,
            "create_time": "2019-08-03T22:29:09.083+0800",
            "owner": {
                "user_id": 48881458551488,
                "name": "林珍-兮哈谈险",
                "avatar_url": "https://images.zsxq.com/FoUTAdkZAwJmLdMZWjj2ru2lSn1B?e=1590940799&token=kIxbL07-8jAj8w1n4s9zv64FuZZNEATmlU_Vm6zD:DJ1mKv--YAYHzdSs2_C_6HbjclE="
            },
            "text": "想到和做到有距离。",
            "likes_count": 0,
            "rewards_count": 0
        },
        {
            "comment_id": 548121282541444,
            "create_time": "2019-08-03T23:36:30.783+0800",
            "owner": {
                "user_id": 111145148128252,
                "name": "当年",
                "avatar_url": "https://images.zsxq.com/FuC1Db_SrZLB-HqXyIzMp70pBWUs?e=1590940799&token=kIxbL07-8jAj8w1n4s9zv64FuZZNEATmlU_Vm6zD:5qTFAsaXQDu7mNdy_OKeMLC9SMw="
            },
            "text": "不错",
            "likes_count": 0,
            "rewards_count": 0
        },
        {
            "comment_id": 548121282448584,
            "create_time": "2019-08-04T00:23:36.939+0800",
            "owner": {
                "user_id": 15484112524842,
                "name": "心愿℃",
                "avatar_url": "https://images.zsxq.com/FopvNSWy81j-etRcwetdhUIs7_Cm?e=1590940799&token=kIxbL07-8jAj8w1n4s9zv64FuZZNEATmlU_Vm6zD:l6J7jrr4DPqbf2Q8ghPGrDIJU_A="
            },
            "text": "知而不行，知则是纸上谈兵，如空中楼阁，不经推敲。行至知成，知行循环依存，共同进化。看似差之毫厘，实则千里。",
            "likes_count": 0,
            "rewards_count": 0,
            "replies_count": 1
        },
        {
            "comment_id": 421848414214848,
            "parent_comment_id": 548121282448584,
            "create_time": "2019-08-04T00:28:01.726+0800",
            "owner": {
                "user_id": 88821825445242,
                "name": "吴都",
                "avatar_url": "https://images.zsxq.com/FrT_S0TjWQlZK1w8iGGtqRxjYaTH?e=1590940799&token=kIxbL07-8jAj8w1n4s9zv64FuZZNEATmlU_Vm6zD:GSHH9u5Ot0wYawCPEomMrLrWD7I="
            },
            "text": "[抱拳][抱拳][抱拳]",
            "likes_count": 0,
            "rewards_count": 0,
            "repliee": {
                "user_id": 15484112524842,
                "name": "心愿℃",
                "avatar_url": "https://images.zsxq.com/FopvNSWy81j-etRcwetdhUIs7_Cm?e=1590940799&token=kIxbL07-8jAj8w1n4s9zv64FuZZNEATmlU_Vm6zD:l6J7jrr4DPqbf2Q8ghPGrDIJU_A="
            }
        },
        {
            "comment_id": 841858515151122,
            "create_time": "2019-08-04T01:34:52.537+0800",
            "owner": {
                "user_id": 2212852121,
                "name": "Kosan",
                "avatar_url": "https://images.zsxq.com/FlcmF02R9UlDg8w3-H9qb2TH0CA2?e=1590940799&token=kIxbL07-8jAj8w1n4s9zv64FuZZNEATmlU_Vm6zD:JRp8W8qOSiBt8UJOVRiY3ZlBaEk="
            },
            "text": "真好，拿你这段话来鞭策自己。",
            "likes_count": 0,
            "rewards_count": 0
        }
    ],
    "likes_count": 84,
    "rewards_count": 6,
    "comments_count": 13,
    "reading_count": 9960,
    "digested": true,
    "sticky": false,
    "create_time": "2019-08-03T18:50:04.332+0800",
    "user_specific": {
        "liked": false,
        "subscribed": false
    }
}